version/__init__.py
tool_version_checker-1.0.0.dist-info/LICENSE
tool_version_checker-1.0.0.dist-info/METADATA
tool_version_checker-1.0.0.dist-info/WHEEL
tool_version_checker-1.0.0.dist-info/top_level.txt
tool_version_checker-1.0.0.dist-info/RECORD
