Metadata-Version: 2.1
Name: tool-version-checker
Version: 1.0.0
Summary: Auto Python Github Projects Version Checker and Updater
Home-page: https://github.com/Toxic-Noob/ToxicNoob_Modules/ToolVersionChecker
Author: ToxicNoob
Author-email: toxicnoob.sl4d3.official@gmail.com
License: UNKNOWN
Platform: UNKNOWN
Classifier: Programming Language :: Python :: 3
Classifier: License :: OSI Approved :: MIT License
Classifier: Operating System :: OS Independent
Requires-Python: >=3.6
License-File: LICENSE
